{
    "version": 1,
    "revision": 0,
    "rules": [
        {
            "primary-output": "x64\\Release\\gui.h.obj",
            "outputs": [
                "D:\\Dev\\RE\\unrealengine-kiocode-base\\unrealengine-kiocode-base\\x64\\Release\\vc143.pdb",
                "x64\\Release\\",
                "D:\\Dev\\RE\\unrealengine-kiocode-base\\unrealengine-kiocode-base\\x64\\Release\\gui.h.ifc"
            ],
            "provides": [
                {
                    "logical-name": "src\\gui\\core\\gui.h",
                    "source-path": "d:\\dev\\re\\unrealengine-kiocode-base\\unrealengine-kiocode-base\\src\\gui\\core\\gui.h",
                    "lookup-method": "absolute"
                }
            ],
            "requires": []
        }
    ]
}